gcsaws/__init__.py
gcsaws/helpers.py
gcsaws/nodes.py
gcsaws/visitor_overview.py
gcsaws/visitor_procedure.py
gcsaws/visitor_save_scripts.py
gcsaws/visitor_validation.py
gcsaws-1.0.0.dist-info/LICENSE
gcsaws-1.0.0.dist-info/METADATA
gcsaws-1.0.0.dist-info/WHEEL
gcsaws-1.0.0.dist-info/top_level.txt
gcsaws-1.0.0.dist-info/RECORD
