Metadata-Version: 2.1
Name: gcsaws
Version: 1.0.0
Summary: GCS implementation for the aws-automation package.
Author-email: Leikt <leikt.solreihin@gmail.com>
Classifier: Programming Language :: Python :: 3
Classifier: License :: OSI Approved :: MIT License
Classifier: Operating System :: OS Independent
Requires-Python: >=3.9
License-File: LICENSE
Requires-Dist: gcscore (>=0.0.22)
Requires-Dist: rich (>=13.3.5)
Provides-Extra: build
Requires-Dist: build (>=0.10.0) ; extra == 'build'
Requires-Dist: twine (>=4.0.2) ; extra == 'build'
